eclipsegraphics/__init__.py
eclipsegraphics/graphics_widget.py
eclipsegraphics-0.1.dist-info/LICENSE
eclipsegraphics-0.1.dist-info/METADATA
eclipsegraphics-0.1.dist-info/WHEEL
eclipsegraphics-0.1.dist-info/top_level.txt
eclipsegraphics-0.1.dist-info/RECORD
