Metadata-Version: 2.1
Name: eclipsegraphics
Version: 0.1
Summary: A python module
Author: Matthew Sanchez
Author-email: 
Classifier: Programming Language :: Python :: 3
Classifier: License :: OSI Approved :: MIT License
Classifier: Operating System :: OS Independent
Requires-Python: >=3.10
License-File: LICENSE
Requires-Dist: PyQt6 >=6.6.1
Requires-Dist: PyQt6-Qt6 >=6.6.1
Requires-Dist: PyQt6-sip >=13.6.0
Requires-Dist: PyQt6-WebEngine >=6.6.0
Requires-Dist: PyOpenGL >=3.1.7
Requires-Dist: PyOpenGL-accelerate >=3.1.7
Requires-Dist: numpy >=1.26.3
Requires-Dist: pillow >=10.2.0
Requires-Dist: skia-python >=87.6
